simple_kfp_task/__init__.py
simple_kfp_task/cli.py
simple_kfp_task/deploykf.py
simple_kfp_task/git_helper.py
simple_kfp_task/pipeline.py
simple_kfp_task/task.py
simple_kfp_task/utils.py
simple_kfp_task-0.0.9.dist-info/LICENSE
simple_kfp_task-0.0.9.dist-info/METADATA
simple_kfp_task-0.0.9.dist-info/WHEEL
simple_kfp_task-0.0.9.dist-info/entry_points.txt
simple_kfp_task-0.0.9.dist-info/top_level.txt
simple_kfp_task-0.0.9.dist-info/RECORD
